qlik_sdk/__init__.py
qlik_sdk/_version.py
qlik_sdk/auth.py
qlik_sdk/auth_type.py
qlik_sdk/config.py
qlik_sdk/errors.py
qlik_sdk/generate_signed_token.py
qlik_sdk/listable.py
qlik_sdk/oauth_utils.py
qlik_sdk/qlik.py
qlik_sdk/rest.py
qlik_sdk/rpc.py
qlik_sdk/utils.py
qlik_sdk/apis/Api_Keys.py
qlik_sdk/apis/Apps.py
qlik_sdk/apis/Audits.py
qlik_sdk/apis/Automations.py
qlik_sdk/apis/Brands.py
qlik_sdk/apis/Collections.py
qlik_sdk/apis/Csp_Origins.py
qlik_sdk/apis/Data_Files.py
qlik_sdk/apis/Extensions.py
qlik_sdk/apis/Groups.py
qlik_sdk/apis/Identity_Providers.py
qlik_sdk/apis/Items.py
qlik_sdk/apis/Licenses.py
qlik_sdk/apis/Notes.py
qlik_sdk/apis/Oauth_Tokens.py
qlik_sdk/apis/Qix.py
qlik_sdk/apis/Questions.py
qlik_sdk/apis/Quotas.py
qlik_sdk/apis/Reload_Tasks.py
qlik_sdk/apis/Reloads.py
qlik_sdk/apis/Roles.py
qlik_sdk/apis/Spaces.py
qlik_sdk/apis/Tenants.py
qlik_sdk/apis/Themes.py
qlik_sdk/apis/Transports.py
qlik_sdk/apis/Users.py
qlik_sdk/apis/Web_Integrations.py
qlik_sdk/apis/Webhooks.py
qlik_sdk/apis/__init__.py
qlik_sdk/interceptors/__init__.py
qlik_sdk/interceptors/retry_response.py
qlik_sdk/interceptors/types.py
qlik_sdk-0.17.0.dist-info/LICENSE
qlik_sdk-0.17.0.dist-info/METADATA
qlik_sdk-0.17.0.dist-info/WHEEL
qlik_sdk-0.17.0.dist-info/top_level.txt
qlik_sdk-0.17.0.dist-info/RECORD
