Metadata-Version: 2.1
Name: qlik-sdk
Version: 0.17.0
Summary: Software Development Kit for Qlik Cloud
Author: qlik-sdk
Author-email: dev.thulhu@gmail.com
Classifier: Programming Language :: Python :: 3
Classifier: License :: OSI Approved :: MIT License
Classifier: Operating System :: OS Independent
Requires-Python: >=3.8
License-File: LICENSE
Requires-Dist: requests ==2.27.1
Requires-Dist: websocket-client ==1.3.2
Requires-Dist: PyJWT[crypto] ==2.4.0
